[
  {
    "policy": "marginal_gain_greedy",
    "type": "heuristic",
    "mean_expected_score": 89.7298,
    "mean_realized_score": 89.7398,
    "mean_realized_score_std": 5.5618,
    "mean_reward": 68.6898,
    "mean_coverage_fraction": 1.0,
    "mean_solved_count": 30.0,
    "mean_steps": 289.6
  },
  {
    "policy": "equal_time",
    "type": "heuristic",
    "mean_expected_score": 84.1009,
    "mean_realized_score": 84.118,
    "mean_realized_score_std": 6.7719,
    "mean_reward": 63.0609,
    "mean_coverage_fraction": 1.0,
    "mean_solved_count": 30.0,
    "mean_steps": 369.56
  },
  {
    "policy": "random",
    "type": "heuristic",
    "mean_expected_score": 83.7145,
    "mean_realized_score": 83.77,
    "mean_realized_score_std": 6.4476,
    "mean_reward": 62.6745,
    "mean_coverage_fraction": 1.0,
    "mean_solved_count": 29.16,
    "mean_steps": 312.62
  },
  {
    "policy": "high_score_first",
    "type": "heuristic",
    "mean_expected_score": 80.6025,
    "mean_realized_score": 80.6078,
    "mean_realized_score_std": 7.3759,
    "mean_reward": 59.5625,
    "mean_coverage_fraction": 1.0,
    "mean_solved_count": 30.0,
    "mean_steps": 425.72
  },
  {
    "policy": "index_order",
    "type": "heuristic",
    "mean_expected_score": 79.3525,
    "mean_realized_score": 79.3332,
    "mean_realized_score_std": 7.5615,
    "mean_reward": 58.3125,
    "mean_coverage_fraction": 1.0,
    "mean_solved_count": 30.0,
    "mean_steps": 437.04
  },
  {
    "policy": "score_time_ratio",
    "type": "heuristic",
    "mean_expected_score": 79.1262,
    "mean_realized_score": 79.1406,
    "mean_realized_score_std": 7.5848,
    "mean_reward": 58.0862,
    "mean_coverage_fraction": 1.0,
    "mean_solved_count": 30.0,
    "mean_steps": 439.56
  },
  {
    "policy": "easy_first",
    "type": "heuristic",
    "mean_expected_score": 76.9187,
    "mean_realized_score": 76.9172,
    "mean_realized_score_std": 7.8172,
    "mean_reward": 55.8787,
    "mean_coverage_fraction": 1.0,
    "mean_solved_count": 30.0,
    "mean_steps": 454.92
  }
]